Workbook

Sheet Danh sách Test Case
A1: Danh sách Test Case
A6: STT | B6: Module | C6: Test Case ID | D6: Tên Test Case | E6: Điều kiện tiền đề | F6: Bước thực hiện | G6: Dữ liệu test | H6: Kết quả mong đợi | I6: Kết quả thực tế | J6: Trạng thái | K6: Mức độ ưu tiên | L6: Người test | M6: Ngày test
A7: =ROW()-6 -> 1 | B7: Người dùng | C7: ="TC-" & TEXT($A7, "000") -> TC-001 | D7: Đăng ký tài khoản Khách hàng mới thành công | E7: SĐT chưa tồn tại trong hệ thống | F7: 1. Mở App khách > Chọn Đăng ký. 2. Nhập thông tin hợp lệ > Nhấn Tiếp tục. 3. Nhập mã OTP gửi về SMS. | G7: Họ tên: Lương Thị Hồng HươngSĐT: 0377974047Email: a@gmail.comPass: Abc@123OTP: 6 số đúng | H7: Tạo tài khoản thành công (verify='verified'), cấp JWT Token và chuyển vào Trang chủ. | J7: Pass | K7: Cao | L7: Bùi Lương Trọng Trí | M7: 46282
A8: =ROW()-6 -> 2 | B8: Người dùng | C8: ="TC-" & TEXT($A8, "000") -> TC-002 | D8: Đăng ký với SĐT đã kích hoạt trước đó | E8: SĐT đã tồn tại với verify='verified' | F8: 1. Mở App khách > Chọn Đăng ký. 2. Nhập SĐT đã tồn tại > Bấm Tiếp tục. | G8: SĐT: 0394351771 | H8: Hệ thống báo lỗi 409 Conflict ("Số điện thoại đã tồn tại"). Không gửi OTP. | J8: Pass | K8: Cao | L8: Bùi Lương Trọng Trí | M8: 46282
A9: =ROW()-6 -> 3 | B9: Người dùng | C9: ="TC-" & TEXT($A9, "000") -> TC-003 | D9: Đăng ký lại với SĐT đang ở trạng thái unverified | E9: SĐT đã tạo bản ghi tạm (unverified) trước đó | F9: 1. Mở App khách > Đăng ký lại bằng SĐT cũ. 2. Nhập họ tên, mật khẩu mới > Nhấn Tiếp tục. 3. Nhập đúng OTP mới. | G9: SĐT unverified cũHọ tên mớiPass mới | H9: Hệ thống ghi đè thông tin mới, gửi OTP mới; xác thực OTP thành công chuyển verify='verified'. | J9: Pass | K9: Trung bình | L9: Bùi Lương Trọng Trí | M9: 46286
A10: =ROW()-6 -> 4 | B10: Người dùng | C10: ="TC-" & TEXT($A10, "000") -> TC-004 | D10: Nhập sai OTP quá 3 lần liên tiếp khi đăng ký | E10: Đang ở màn hình nhập OTP đăng ký | F10: 1. Nhập sai OTP lần 1 > Bấm Xác nhận. 2. Nhập sai lần 2 > Bấm Xác nhận. 3. Nhập sai lần 3 > Bấm Xác nhận. | G10: OTP: 000000 (sai) | H10: OTP bị hủy (is_expired=TRUE), khóa yêu cầu từ Device/IP 15 phút kèm cảnh báo. | J10: Block | K10: Cao
A11: =ROW()-6 -> 5 | B11: Người dùng | C11: ="TC-" & TEXT($A11, "000") -> TC-005 | D11: Đăng ký với Email sai định dạng RFC 5322 | F11: 1. Mở màn hình đăng ký 2. Nhập email sai định dạng 3. Nhập các trường còn lại hợp lệ 4. Bấm 'Tiếp tục' | G11: Email: abc@@gmail | H11: Hệ thống báo lỗi định dạng Email không hợp lệ | J11: Pass | K11: Cao | L11: Bùi Lương Trọng Trí | M11: 46283
A12: =ROW()-6 -> 6 | B12: Người dùng | C12: ="TC-" & TEXT($A12, "000") -> TC-006 | D12: Đăng ký với SĐT sai định dạng (không đủ 10 số) | F12: 1. Mở màn hình đăng ký 2. Nhập SĐT sai định dạng 3. Nhập các trường còn lại hợp lệ 4. Bấm 'Tiếp tục' | G12: SĐT: 09123456 (8 số) | H12: Hệ thống báo lỗi validate định dạng SĐT, không cho phép submit | J12: Pass | K12: Cao | L12: Bùi Lương Trọng Trí | M12: 46283
A13: =ROW()-6 -> 7 | B13: Người dùng | C13: ="TC-" & TEXT($A13, "000") -> TC-007 | D13: Đăng nhập tài khoản sai mật khẩu quá 5 lần | E13: Tài khoản khách hàng đang active | F13: 1. Nhập đúng SĐT 2. Nhập sai mật khẩu liên tiếp 5 lần 3. Nhấn Đăng nhập. | G13: SĐT: 0394351771Pass: SaiPass123 | H13: Báo lỗi 401; sau lần 5 tạm khóa đăng nhập của SĐT trong 15 phút. | J13: Block | K13: Cao
A14: =ROW()-6 -> 8 | B14: Người dùng | C14: ="TC-" & TEXT($A14, "000") -> TC-008 | D14: Đăng ký với mật khẩu ít hơn 6 ký tự | F14: 1. Mở màn hình đăng ký 2. Nhập mật khẩu < 6 ký tự 3. Bấm 'Tiếp tục | G14: Mật khẩu: Ab@1 | H14: Hệ thống báo lỗi mật khẩu phải từ 6-160 ký tự | J14: Pass | K14: Cao | L14: Bùi Lương Trọng Trí | M14: 46283
A15: =ROW()-6 -> 9 | B15: Người dùng | C15: ="TC-" & TEXT($A15, "000") -> TC-009 | D15: Đăng ký với mật khẩu nhiều hơn 160 ký tự | F15: 1. Mở màn hình đăng ký 2. Nhập mật khẩu > 160 ký tự 3. Bấm 'Tiếp tục' | G15: Mật khẩu gồm 161 ký tự | H15: Hệ thống báo lỗi mật khẩu phải từ 6-160 ký tự | J15: Pass | K15: Cao | L15: Bùi Lương Trọng Trí | M15: 46283
A16: =ROW()-6 -> 10 | B16: Người dùng | C16: ="TC-" & TEXT($A16, "000") -> TC-010 | D16: Đăng ký với mật khẩu thiếu chữ viết hoa | F16: 1. Mở màn hình đăng ký 2. Nhập mật khẩu không có chữ hoa 3. Bấm 'Tiếp tục' | G16: Mật khẩu: abc@123 | H16: Hệ thống báo lỗi mật khẩu phải có ít nhất 1 chữ hoa | J16: Pass | K16: Cao | L16: Bùi Lương Trọng Trí | M16: 46283
A17: =ROW()-6 -> 11 | B17: Người dùng | C17: ="TC-" & TEXT($A17, "000") -> TC-011 | D17: Đăng ký với mật khẩu thiếu chữ số | F17: 1. Mở màn hình đăng ký 2. Nhập mật khẩu không có số 3. Bấm 'Tiếp tục' | G17: Mật khẩu: Abc@xyz | H17: Hệ thống báo lỗi mật khẩu phải có ít nhất 1 chữ số | J17: Pass | K17: Cao | L17: Bùi Lương Trọng Trí | M17: 46283
A18: =ROW()-6 -> 12 | B18: Người dùng | C18: ="TC-" & TEXT($A18, "000") -> TC-012 | D18: Đăng ký với mật khẩu thiếu ký tự đặc biệt | F18: 1. Mở màn hình đăng ký 2. Nhập mật khẩu không có ký tự đặc biệt 3. Bấm 'Tiếp tục' | G18: Mật khẩu: Abc12345 | H18: Hệ thống báo lỗi mật khẩu phải có ít nhất 1 ký tự đặc biệt | J18: Pass | K18: Cao | L18: Bùi Lương Trọng Trí | M18: 46283
A19: =ROW()-6 -> 13 | B19: Người dùng | C19: ="TC-" & TEXT($A19, "000") -> TC-013 | D19: Cơ chế Single Active Session (Đăng nhập thiết bị B đá thiết bị A) | E19: Tài khoản đang đăng nhập hoạt động trên Thiết bị A | F19: 1. Dùng tài khoản đó đăng nhập trên Thiết bị B. 2. Trên Thiết bị A, thực hiện gọi 1 API bất kỳ. | G19: Cùng 1 tài khoản khách hàng | H19: Thiết bị B đăng nhập thành công. Thiết bị A nhận lỗi 401 (SESSION_TERMINATED_BY_ANOTHER_DEVICE), đếm ngược 15s và đẩy về màn Đăng nhập. | J19: Block | K19: Cao
A20: =ROW()-6 -> 14 | B20: Người dùng | C20: ="TC-" & TEXT($A20, "000") -> TC-014 | D20: Nhập mã OTP đã hết hạn (> 3 phút) | E20: OTP đã được sinh quá 3 phút trước | F20: 1. Nhập đúng mã OTP nhưng đã hết hạn 2. Bấm xác nhận | G20: OTP hết hạn (expired_at < NOW()) | H20: Hệ thống báo lỗi mã OTP đã hết hạn | J20: Pass | K20: Cao | L20: Bùi Lương Trọng Trí | M20: 46283
A21: =ROW()-6 -> 15 | B21: Người dùng | C21: ="TC-" & TEXT($A21, "000") -> TC-015 | D21: Bấm 'Gửi lại mã' sau khi đủ 120 giây | E21: Đang ở màn hình OTP, đã quá 120 giây | F21: 1. Bấm nút 'Gửi lại mã' sau 120 giây | H21: OTP cũ bị huỷ (is_expired=TRUE); OTP mới được sinh với hạn 3 phút mới và gửi SMS | J21: Pass | K21: Cao | L21: Bùi Lương Trọng Trí | M21: 46283
A22: =ROW()-6 -> 16 | B22: Người dùng | C22: ="TC-" & TEXT($A22, "000") -> TC-016 | D22: Gửi lại mã OTP vượt quá 3 lần trong 15 phút | E22: Đã gửi lại OTP 3 lần trong vòng 15 phút cho 1 SĐT | F22: 1. Tiếp tục bấm 'Gửi lại mã' lần thứ 4 trong vòng 15 phút | G22: Số lần gửi lại: lần 4 trong 15 phút | H22: Hệ thống trả lỗi 429 Too Many Requests, không gửi thêm OTP | J22: Pass | K22: Trung bình | M22: 46287
A23: =ROW()-6 -> 17 | B23: Người dùng | C23: ="TC-" & TEXT($A23, "000") -> TC-017 | D23: Thoát App khi đang ở màn hình OTP và quay lại đăng ký cùng SĐT trong vòng 3 phút | E23: Đã đăng ký với SĐT X (verify='unverified'), OTP cũ còn hạn (< 3 phút) | F23: 1. Thoát App khi đang ở màn hình nhập OTP 2. Mở lại App, nhập lại cùng SĐT X để đăng ký 3. Bấm 'Tiếp tục' | G23: SĐT X, OTP cũ còn hạn | H23: Backend nhận diện OTP cũ còn hạn, trả cờ OTP_ALREADY_SENT kèm số giây còn lại; Client vào thẳng màn hình OTP với đếm ngược tiếp tục, không gửi SMS mới | I23: Hiện thông báo không thể gửi OTP, không quay lại màn hình nhập OTP | J23: Fail | K23: Trung bình | L23: Bùi Lương Trọng Trí | M23: 46283
A24: =ROW()-6 -> 18 | B24: Người dùng | C24: ="TC-" & TEXT($A24, "000") -> TC-018 | D24: Khôi phục mật khẩu (Quên mật khẩu) qua SMS OTP | E24: Tài khoản khách hàng tồn tại trong hệ thống | F24: 1. Bấm Quên mật khẩu > Nhập SĐT. 2. Nhập đúng OTP nhận được. 3. Nhập mật khẩu mới thỏa điều kiện > Bấm Xác nhận. | G24: SĐT: 0394351771Pass mới: NewPass@2026 | H24: Đổi mật khẩu thành công, toàn bộ session cũ bị revoked (reason='password_changed'), buộc đăng nhập lại bằng mật khẩu mới. | J24: Pass | K24: Cao | L24: Bùi Lương Trọng Trí | M24: 46283
A25: =ROW()-6 -> 19 | B25: Người dùng | C25: ="TC-" & TEXT($A25, "000") -> TC-019 | D25: Đăng nhập thành công với SĐT và mật khẩu đúng | E25: Tài khoản tồn tại, verify='verified', role='customer' | F25: 1. Nhập SĐT và Mật khẩu đúng 2. Bấm 'Đăng nhập' | G25: SĐT: 0394351771; Mật khẩu đúng | H25: Đăng nhập thành công; trả về access_token và refresh_token; tạo users_session mới status='active' | J25: Pass | K25: Cao | L25: Bùi Lương Trọng Trí | M25: 46283
A26: =ROW()-6 -> 20 | B26: Người dùng | C26: ="TC-" & TEXT($A26, "000") -> TC-020 | D26: Đăng nhập với SĐT không tồn tại trong hệ thống | E26: SĐT chưa từng đăng ký | F26: 1. Nhập SĐT không tồn tại và Mật khẩu bất kỳ 2. Bấm 'Đăng nhập' | G26: SĐT: 0999999999 (không tồn tại) | H26: Trả lỗi 401 Unauthorized: 'Số điện thoại hoặc mật khẩu không chính xác' | J26: Pass | K26: Cao | L26: Bùi Lương Trọng Trí | M26: 46283
A27: =ROW()-6 -> 21 | B27: Người dùng | C27: ="TC-" & TEXT($A27, "000") -> TC-021 | D27: Đăng nhập với tài khoản có role khác 'customer' | E27: Tài khoản tồn tại với role='partner' hoặc 'admin' | F27: 1. Nhập SĐT của tài khoản partner/admin và mật khẩu đúng 2. Bấm 'Đăng nhập' (trên App khách hàng) | G27: SĐT partner/admin | H27: Trả lỗi 401 Unauthorized do role != 'customer' | J27: Pass | K27: Cao | L27: Bùi Lương Trọng Trí | M27: 46286
A28: =ROW()-6 -> 22 | B28: Người dùng | C28: ="TC-" & TEXT($A28, "000") -> TC-022 | D28: Đăng nhập khi tài khoản đang bị khoá ('suspended') | E28: Tài khoản tồn tại, verify='suspended' | F28: 1. Nhập SĐT và mật khẩu đúng của tài khoản suspended 2. Bấm 'Đăng nhập' | G28: SĐT tài khoản suspended | H28: Trả lỗi 403 Forbidden: 'Tài khoản đã bị tạm khóa' | J28: Block | K28: Cao
A29: =ROW()-6 -> 23 | B29: Người dùng | C29: ="TC-" & TEXT($A29, "000") -> TC-023 | D29: Đăng nhập sai mật khẩu | E29: Tài khoản tồn tại, verify='verified' | F29: 1. Nhập đúng SĐT, sai mật khẩu 2. Bấm 'Đăng nhập' | G29: Mật khẩu sai | H29: Trả lỗi 401 Unauthorized: 'Sai thông tin đăng nhập' | J29: Pass | K29: Cao | L29: Bùi Lương Trọng Trí | M29: 46286
A30: =ROW()-6 -> 24 | B30: Người dùng | C30: ="TC-" & TEXT($A30, "000") -> TC-024 | D30: Đăng nhập sai mật khẩu 5 lần liên tiếp | E30: Tài khoản tồn tại, verify='verified' | F30: 1. Nhập sai mật khẩu liên tiếp 5 lần | G30: 5 lần nhập sai mật khẩu | H30: Tài khoản tạm khoá đăng nhập trong 15 phút; hiển thị thông báo 'Tài khoản tạm thời bị khóa đăng nhập do nhập sai 5 lần. Vui lòng thử lại sau 15 phút hoặc sử dụng Quên mật khẩu' | J30: Block | K30: Cao
A31: =ROW()-6 -> 25 | B31: Người dùng | C31: ="TC-" & TEXT($A31, "000") -> TC-025 | D31: Đăng nhập lại trong thời gian đang bị tạm khoá do sai mật khẩu | E31: Tài khoản đang bị khoá đăng nhập 15 phút do sai mật khẩu 5 lần | F31: 1. Nhập đúng mật khẩu trong thời gian bị khoá 2. Bấm 'Đăng nhập' | G31: Mật khẩu đúng nhưng đang trong 15 phút khoá | H31: Hệ thống vẫn từ chối đăng nhập và hiển thị thông báo còn thời gian khoá | J31: Block | K31: Trung bình
A32: =ROW()-6 -> 26 | B32: Người dùng | C32: ="TC-" & TEXT($A32, "000") -> TC-026 | D32: Đăng xuất thành công | E32: Khách hàng đã đăng nhập, có session active | F32: 1. Bấm 'Đăng xuất' | H32: Session hiện tại chuyển status='revoked', reason='user_logout'; token trên thiết bị bị vô hiệu hoá; chuyển về màn hình đăng nhập | J32: Pass | K32: Cao | L32: Bùi Lương Trọng Trí | M32: 46283
A33: =ROW()-6 -> 27 | B33: Người dùng | C33: ="TC-" & TEXT($A33, "000") -> TC-027 | D33: Yêu cầu quên mật khẩu với SĐT chưa đăng ký | E33: SĐT không tồn tại trong hệ thống | F33: 1. Bấm 'Quên mật khẩu' 2. Nhập SĐT không tồn tại 3. Bấm xác nhận | G33: SĐT không tồn tại | H33: Hệ thống báo lỗi SĐT không tồn tại, không gửi OTP | J33: Pass | K33: Cao | L33: Bùi Lương Trọng Trí | M33: 46283
A34: =ROW()-6 -> 28 | B34: Người dùng | C34: ="TC-" & TEXT($A34, "000") -> TC-028 | D34: Yêu cầu quên mật khẩu với SĐT hợp lệ đã đăng ký | E34: SĐT tồn tại và đã verified | F34: 1. Bấm 'Quên mật khẩu' 2. Nhập SĐT hợp lệ 3. Bấm xác nhận | G34: SĐT: 0912345678 (đã tồn tại) | H34: Hệ thống sinh OTP SMS 6 số, hạn 3 phút, type='reset_password' và gửi về SĐT | J34: Pass | K34: Cao | L34: Bùi Lương Trọng Trí | M34: 46283
A35: =ROW()-6 -> 29 | B35: Người dùng | C35: ="TC-" & TEXT($A35, "000") -> TC-029 | D35: Cập nhật hồ sơ với Ngày sinh lớn hơn ngày hiện tại | E35: Khách hàng đã đăng nhập | F35: 1. Vào mục Hồ sơ cá nhân. 2. Chọn Ngày sinh trong tương lai. 3. Bấm Lưu thay đổi. | G35: DOB: Ngày mai | H35: Hệ thống chặn không cho chọn ngày tương lai | J35: Pass | K35: Trung bình | L35: Bùi Lương Trọng Trí | M35: 46282
A36: =ROW()-6 -> 30 | B36: Thợ & KYC | C36: ="TC-" & TEXT($A36, "000") -> TC-030 | D36: Thợ nộp hồ sơ đăng ký mới đầy đủ thông tin hợp lệ | E36: SĐT và CCCD chưa từng đăng ký thợ | F36: 1. Mở App thợ > Trở thành thợ FixHub. 2. Nhập thông tin cá nhân, chọn khu vực, kỹ năng. 3. Tải ảnh CCCD 2 mặt (<=5MB). 4. Bấm Gửi hồ sơ. | G36: Họ tên: Trần Văn BSĐT: 0987654321CCCD: 0123456789Ảnh: jpg < 5MB | H36: Hồ sơ được tạo thành công với trạng thái pending, users.verify='unverified'. Ảnh lưu Private Bucket. | J36: Block | K36: Cao
A37: =ROW()-6 -> 31 | B37: Thợ & KYC | C37: ="TC-" & TEXT($A37, "000") -> TC-031 | D37: Nộp hồ sơ thợ với số CCCD đã tồn tại | E37: CCCD đã có trong bảng technician_profile | F37: 1. Điền form đăng ký thợ. 2. Nhập CCCD đã tồn tại trên hệ thống. 3. Bấm Gửi hồ sơ. | G37: CCCD: 0123456789 (đã có) | H37: Báo lỗi 409 Conflict ("Số điện thoại hoặc Số CCCD này đã tồn tại trên hệ thống"). | J37: Block | K37: Cao
A38: =ROW()-6 -> 32 | B38: Thợ & KYC | C38: ="TC-" & TEXT($A38, "000") -> TC-032 | D38: Thợ đăng nhập khi hồ sơ đang chờ duyệt (pending) | E38: Tài khoản thợ có approval_status='pending' | F38: 1. Mở App thợ. 2. Nhập đúng SĐT và mật khẩu. 3. Bấm Đăng nhập. | G38: SĐT thợ đang pending | H38: Chặn đăng nhập, trả về HTTP 403 Forbidden kèm thông báo hồ sơ đang chờ xét duyệt. | J38: Block | K38: Cao
A39: =ROW()-6 -> 33 | B39: Thợ & KYC | C39: ="TC-" & TEXT($A39, "000") -> TC-033 | D39: Admin phê duyệt hồ sơ thợ hợp lệ | E39: Hồ sơ thợ đang ở trạng thái pending | F39: 1. Admin vào Quản lý thợ > Danh sách chờ duyệt. 2. Mở chi tiết đối soát thông tin và ảnh CCCD. 3. Bấm Phê duyệt hồ sơ. | G39: ID hồ sơ hợp lệ | H39: Cập nhật approval_status='approved', users.verify='verified'. Gửi SMS thông báo phê duyệt thành công cho thợ. | J39: Block | K39: Cao
A40: =ROW()-6 -> 34 | B40: Thợ & KYC | C40: ="TC-" & TEXT($A40, "000") -> TC-034 | D40: Admin từ chối hồ sơ thợ kèm lý do | E40: Hồ sơ thợ đang ở trạng thái pending | F40: 1. Mở chi tiết hồ sơ chờ duyệt. 2. Bấm Từ chối. 3. Nhập lý do từ chối > Xác nhận. | G40: Lý do: "Ảnh CCCD mờ, không rõ số" | H40: Cập nhật approval_status='rejected', lưu rejection_reason. Bắn SMS thông báo từ chối kèm lý do cho thợ. | J40: Block | K40: Cao
A41: =ROW()-6 -> 35 | B41: Thợ & KYC | C41: ="TC-" & TEXT($A41, "000") -> TC-035 | D41: Đăng nhập thành công sau khi được Admin duyệt | E41: Thợ đã được Admin duyệt (approved) | F41: 1. Mở App thợ. 2. Nhập đúng SĐT và mật khẩu. 3. Bấm Đăng nhập. | G41: SĐT & Pass thợ approved | H41: Cấp JWT Token thành công và chuyển thẳng vào Màn hình Trang chủ (Home Dashboard). | J41: Block | K41: Cao
A42: =ROW()-6 -> 36 | B42: Tìm kiếm & Điều phối | C42: ="TC-" & TEXT($A42, "000") -> TC-036 | D42: Admin xem danh sách Ticket unassigned ở màn Nhiệm vụ | E42: Có ít nhất 1 ticket ở trạng thái unassigned | F42: 1. Admin vào màn Nhiệm vụ. 2. Chọn nhóm Chưa gán. | G42: Ticket unassigned | H42: Danh sách hiển thị các ticket unassigned với mã đơn, dịch vụ, địa chỉ, giờ hẹn. | J42: Pass | K42: Cao | L42: Bùi Lương Trọng Trí | M42: 46287
A43: =ROW()-6 -> 37 | B43: Tìm kiếm & Điều phối | C43: ="TC-" & TEXT($A43, "000") -> TC-037 | D43: Ticket sau khi gán hiển thị tên thợ | E43: Admin vừa gán ticket cho thợ | F43: 1. Quay lại màn Nhiệm vụ. 2. Kiểm tra đơn. | G43: Ticket assigned | H43: Ticket đã gán kèm tên thợ, technician_id đúng thợ. | J43: Pass | K43: Cao | L43: Bùi Lương Trọng Trí | M43: 46287
A44: =ROW()-6 -> 38 | B44: Tìm kiếm & Điều phối | C44: ="TC-" & TEXT($A44, "000") -> TC-038 | D44: Thợ thấy Ticket mới ở nhiệm vụ mới gần bạn và nhiệm vụ mới ở tab nhiệm vụ | E44: Admin vừa gán ticket cho thợ A | F44: 1. Thợ A mở App thợ > Nhiệm vụ > Nhiệm vụ mới. | G44: Ticket assigned cho thợ A | H44: Ticket xuất hiện trong danh sách nhiệm vụ mới | J44: Pass | K44: Cao | L44: Bùi Lương Trọng Trí | M44: 46287
A45: =ROW()-6 -> 39 | B45: Tìm kiếm & Điều phối | C45: ="TC-" & TEXT($A45, "000") -> TC-039 | D45: Chi tiết Ticket ở App thợ hiển thị đầy đủ thông tin công việc | E45: Ticket assigned cho thợ, đơn có ghi chú và ảnh | F45: 1. Thợ mở chi tiết ticket. | G45: Ticket có ghi chú và ảnh | H45: Hiển thị đúng dịch vụ, địa chỉ, giờ hẹn, ghi chú khách và ảnh đính kèm. | J45: Pass | K45: Trung bình | L45: Bùi Lương Trọng Trí | M45: 46287
A46: =ROW()-6 -> 40 | B46: Tìm kiếm & Điều phối | C46: ="TC-" & TEXT($A46, "000") -> TC-040 | D46: Tìm thợ theo tên trong trang gán kỹ thuật viên | E46: Trang gán kỹ thuật viên đang mở, có nhiều thợ | F46: 1. Nhập một phần tên thợ vào ô tìm kiếm. | G46: Từ khóa: tên thợ | H46: Danh sách lọc còn các thợ có tên chứa từ khóa. | J46: Pass | K46: Trung bình | L46: Bùi Lương Trọng Trí | M46: 46287
A47: =ROW()-6 -> 41 | B47: Tìm kiếm & Điều phối | C47: ="TC-" & TEXT($A47, "000") -> TC-041 | D47: Tìm thợ theo số điện thoại trong trang gán kỹ thuật viên | E47: Trang gán kỹ thuật viên đang mở, có nhiều thợ | F47: 1. Nhập SĐT thợ vào ô tìm kiếm. | G47: Từ khóa: SĐT thợ | H47: Hiển thị đúng thợ có SĐT khớp. | J47: Pass | K47: Trung bình | L47: Bùi Lương Trọng Trí | M47: 46287
A48: =ROW()-6 -> 42 | B48: Tìm kiếm & Điều phối | C48: ="TC-" & TEXT($A48, "000") -> TC-042 | D48: Lọc Ticket theo trạng thái ở màn Nhiệm vụ | E48: Có ticket ở nhiều trạng thái khác nhau | F48: 1. Chọn bộ lọc trạng thái unassigned/assigned/accepted lần lượt. | G48: Ticket nhiều trạng thái | H48: Danh sách chỉ hiển thị ticket đúng trạng thái đã chọn. | J48: Pass | K48: Trung bình | L48: Bùi Lương Trọng Trí | M48: 46287
A49: =ROW()-6 -> 43 | B49: Tìm kiếm & Điều phối | C49: ="TC-" & TEXT($A49, "000") -> TC-043 | D49: Tìm Ticket theo mã đơn hàng | E49: Có nhiều ticket trong hệ thống | F49: 1. Nhập mã đơn vào ô tìm kiếm ở màn Nhiệm vụ. | G49: Mã đơn tồn tại | H49: Hiển thị đúng ticket của đơn có mã đó. | J49: Pass | K49: Trung bình | L49: Bùi Lương Trọng Trí | M49: 46287
A50: =ROW()-6 -> 44 | B50: Tìm kiếm & Điều phối | C50: ="TC-" & TEXT($A50, "000") -> TC-044 | D50: Gán thợ không làm thay đổi trạng thái đơn hàng | E50: Đơn confirmed, ticket unassigned | F50: 1. Admin gán ticket cho thợ. 2. Kiểm tra orders.status. | G50: Đơn confirmed | H50: tickets.status chuyển assigned, orders.status vẫn là confirmed (hai chuỗi trạng thái độc lập). | J50: Pass | K50: Trung bình | L50: Bùi Lương Trọng Trí | M50: 46287
A51: =ROW()-6 -> 45 | B51: Tìm kiếm & Điều phối | C51: ="TC-" & TEXT($A51, "000") -> TC-045 | D51: Thợ cũ không còn thấy Ticket sau khi bị đổi | E51: Admin vừa đổi thợ khỏi thợ cũ | F51: 1. Thợ cũ mở App thợ > Việc được giao/Việc đã nhận. | G51: Thợ cũ | H51: Ticket không còn xuất hiện trong danh sách công việc của thợ cũ. | J51: Pass | K51: Cao | L51: Bùi Lương Trọng Trí | M51: 46287
A52: =ROW()-6 -> 46 | B52: Tìm kiếm & Điều phối | C52: ="TC-" & TEXT($A52, "000") -> TC-046 | D52: Thợ mới thấy Ticket ở trạng thái assigned và phải xác nhận lại | E52: Admin vừa đổi sang thợ mới | F52: 1. Thợ mới mở App thợ > Việc được giao. | G52: Thợ mới | H52: Ticket hiển thị ở Việc được giao với trạng thái chờ xác nhận, thợ mới phải bấm Xác nhận nhận việc. | J52: Pass | K52: Cao | L52: Bùi Lương Trọng Trí | M52: 46287
A53: =ROW()-6 -> 47 | B53: Tìm kiếm & Điều phối | C53: ="TC-" & TEXT($A53, "000") -> TC-047 | D53: Khách thấy thông tin thợ mới sau khi Admin đổi thợ | E53: Ticket đã được đổi sang thợ mới | F53: 1. Khách mở chi tiết đơn/ticket. | G53: Đơn có thợ mới | H53: Thông tin thợ hiển thị là thợ mới, không còn hiển thị thông tin thợ cũ. | J53: Pass | K53: Trung bình | L53: Bùi Lương Trọng Trí | M53: 46287
... A56: =ROW()-6 -> 50 | B56: Tìm kiếm & Điều phối | C56: ="TC-" & TEXT($A56, "000") -> TC-050 | D56: Thợ mới từ chối nhận việc sau khi được đổi | E56: Ticket vừa được đổi sang thợ mới, trạng thái assigned | F56: 1. Thợ mới mở ticket > Bấm Từ chối. | G56: Thợ mới | H56: tickets.status về unassigned, technician_id=NULL, log action='rejected', Web Admin hiện cảnh báo đỏ. | J56: Pass | K56: Cao | L56: Bùi Lương Trọng Trí | M56: 46287
A57: =ROW()-6 -> 51 | B57: Tìm kiếm & Điều phối | C57: ="TC-" & TEXT($A57, "000") -> TC-051 | D57: Thợ mới xác nhận nhận việc sau khi được đổi | E57: Ticket vừa được đổi sang thợ mới, trạng thái assigned | F57: 1. Thợ mới mở ticket > Bấm Xác nhận nhận việc. | G57: Thợ mới | H57: tickets.status chuyển accepted, log action='accepted', khách nhận Push có thợ nhận đơn. | J57: Block | K57: Trung bình
A58: =ROW()-6 -> 52 | B58: Tìm kiếm & Điều phối | C58: ="TC-" & TEXT($A58, "000") -> TC-052 | D58: Tìm kiếm và lọc dịch vụ | E58: Đã có danh mục và dịch vụ trên hệ thống | F58: 1. Khách vào màn hình Tìm kiếm. 2. Nhập từ khóa tìm kiếm | G58: Từ khóa: "máy lạnh" | H58: Danh sách dịch vụ hiển thị đúng theo từ khóa | J58: Pass | K58: Trung bình | L58: Bùi Lương Trọng Trí | M58: 46282
A59: =ROW()-6 -> 53 | B59: Tìm kiếm & Điều phối | C59: ="TC-" & TEXT($A59, "000") -> TC-053 | D59: Sắp xếp dịch vụ theo giá tăng dần | F59: 1. Chọn sắp xếp 'Giá tăng dần' 2. Xem kết quả | G59: Sắp xếp: base_price ASC | H59: Danh sách dịch vụ được sắp xếp tăng dần theo giá | J59: Block | K59: thấp
A60: =ROW()-6 -> 54 | B60: Tìm kiếm & Điều phối | C60: ="TC-" & TEXT($A60, "000") -> TC-054 | D60: Sắp xếp dịch vụ theo giá giảm dần | F60: 1. Chọn sắp xếp 'Giá giảm dần' 2. Xem kết quả | G60: Sắp xếp: base_price DESC | H60: Danh sách dịch vụ được sắp xếp giảm dần theo giá | J60: Block | K60: thấp
A61: =ROW()-6 -> 55 | B61: Tìm kiếm & Điều phối | C61: ="TC-" & TEXT($A61, "000") -> TC-055 | D61: Chặn gán thợ khi thợ không hoạt động | E61: Thợ đang tắt trạng thái hoạt động | F61: 1. Admin vào Nhiệm vụ. 2. Chọn thợ từ danh sách gợi ý. 3. Bấm Gán việc. | G61: Thợ tắt hoạt động | H61: Danh sách gợi ý thợ không có chứa thợ không hoạt động | J61: Block | K61: Cao
A62: =ROW()-6 -> 56 | B62: Tìm kiếm & Điều phối | C62: ="TC-" & TEXT($A62, "000") -> TC-056 | D62: Tự động sinh Ticket ở trạng thái unassigned khi Order confirmed | E62: Đơn hàng chuyển sang trạng thái confirmed | F62: Admin bấm Xác nhận. | G62: Đơn hàng hợp lệ | H62: Hệ thống tự động tạo 01 bản ghi tickets với status='unassigned', không tự động gán thợ. | J62: Pass | K62: Cao | L62: Bùi Lương Trọng Trí | M62: 46282
A63: =ROW()-6 -> 57 | B63: Tìm kiếm & Điều phối | C63: ="TC-" & TEXT($A63, "000") -> TC-057 | D63: Admin gán Ticket thủ công cho thợ phù hợp | E63: Ticket đang ở trạng thái unassigned | F63: 1. Admin vào Nhiệm vụ. 2. Chọn thợ từ danh sách gợi ý. 3. Bấm Gán việc. | G63: Thợ thỏa mãn khu vực & chuyên môn | H63: tickets.status chuyển sang assigned, lưu log action='assigned', bắn Push thông báo việc mới cho thợ. | J63: Pass | K63: Cao | L63: Bùi Lương Trọng Trí | M63: 46282
A64: =ROW()-6 -> 58 | B64: Tìm kiếm & Điều phối | C64: ="TC-" & TEXT($A64, "000") -> TC-058 | D64: Thợ bấm "Xác nhận nhận việc" (Accept Ticket) | E64: Ticket được gán cho thợ (status='assigned') | F64: 1. Thợ mở thông báo/mục Việc được giao. 2. Xem chi tiết Ticket. 3. Bấm "Xác nhận nhận việc". | G64: Ticket ID tương ứng | H64: tickets.status chuyển sang accepted, ghi log action='accepted', bắn Push thông báo cho khách hàng đã có thợ nhận đơn. | J64: Pass | K64: Cao | L64: Bùi Lương Trọng Trí | M64: 46282
A65: =ROW()-6 -> 59 | B65: Tìm kiếm & Điều phối | C65: ="TC-" & TEXT($A65, "000") -> TC-059 | D65: Thợ bấm "Từ chối" nhận việc | E65: Ticket được gán cho thợ (status='assigned') | F65: 1. Thợ mở chi tiết Ticket được giao. 2. Bấm Từ chối | H65: tickets.status trở về unassigned, technician_id=NULL, ghi log action='rejected'. Web Admin hiện cảnh báo đỏ. | J65: Pass | K65: Cao | L65: Bùi Lương Trọng Trí | M65: 46282
A66: =ROW()-6 -> 60 | B66: Tìm kiếm & Điều phối | C66: ="TC-" & TEXT($A66, "000") -> TC-060 | D66: Ticket ở trạng thái assigned quá 15 phút thợ không phản hồi | E66: Thợ được gán việc nhưng chưa Accept/Reject | F66: Chờ quá 15 phút kể từ thời điểm Admin gán việc. | G66: Ticket assigned > 15 phút | H66: Web Admin Portal hiển thị tag cảnh báo màu vàng ("Chờ phản hồi >15p") để Admin can thiệp Re-assign. | J66: Block | K66: Trung bình
A67: =ROW()-6 -> 61 | B67: Tìm kiếm & Điều phối | C67: ="TC-" & TEXT($A67, "000") -> TC-061 | D67: Admin Re-assign (Đổi thợ khác) khi Ticket đang accepted | E67: Ticket đang accepted nhưng thợ gặp sự cố | F67: 1. Admin mở Ticket đang accepted. 2. Bấm Đổi thợ > Chọn thợ mới > Nhập lý do. 3. Xác nhận gán. | G67: Thợ mới, Lý do đổi | H67: technician_id đổi sang thợ mới, trạng thái về assigned, bắn Push hủy việc cho thợ cũ và gửi việc cho thợ mới. | J67: Pass | K67: Cao | L67: Bùi Lương Trọng Trí | M67: 46282
A68: =ROW()-6 -> 62 | B68: Tìm kiếm & Điều phối | C68: ="TC-" & TEXT($A68, "000") -> TC-062 | D68: Khách hàng hủy đơn khi Admin đã gán thợ (Ticket assigned/accepted) | E68: Order đã confirmed, Ticket đang ở trạng thái assigned hoặc accepted | F68: 1. Khách hàng vào chi tiết đơn hàng 2. Bấm 'Hủy đơn' | G68: Ticket đang assigned/accepted | H68: Backend cập nhật orders.status='cancelled' và tickets.status='cancelled'; bắn Push cho thợ báo đơn bị hủy; Ticket biến mất khỏi danh sách việc của thợ | J68: Block | K68: Cao
A69: =ROW()-6 -> 63 | B69: Tìm kiếm & Điều phối | C69: ="TC-" & TEXT($A69, "000") -> TC-063 | D69: Khách hàng hủy đơn khi Ticket vẫn đang unassigned | E69: Order đã confirmed, Ticket chưa được gán thợ nào (unassigned) | F69: 1. Khách hàng vào chi tiết đơn hàng 2. Bấm 'Hủy đơn' | G69: Ticket đang unassigned | H69: Backend cập nhật orders.status='cancelled' và tickets.status='cancelled'; do chưa gán thợ nên không cần bắn Push cho thợ nào | J69: Block | K69: Cao
A70: =ROW()-6 -> 64 | B70: Tìm kiếm & Điều phối | C70: ="TC-" & TEXT($A70, "000") -> TC-064 | D70: Ticket bị từ chối nhiều lần liên tiếp bởi nhiều thợ khác nhau | E70: Ticket đã bị ít nhất 2 thợ khác nhau từ chối liên tiếp | F70: 1. Admin gán Ticket cho thợ A -> thợ A từ chối 2. Admin gán lại cho thợ B -> thợ B từ chối 3. Admin mở lại chi tiết Ticket, xem lịch sử | G70: 2 lượt từ chối liên tiếp từ 2 thợ khác nhau | H70: Mỗi lần từ chối tạo 1 bản ghi log riêng trong ticket_assignment_logs; Web Admin Portal hiển thị đầy đủ lịch sử từ chối (thợ, thời điểm, lý do) để Admin nắm ngữ cảnh trước khi gán lại | J70: Block | K70: Cao
A71: =ROW()-6 -> 65 | B71: Tìm kiếm & Điều phối | C71: ="TC-" & TEXT($A71, "000") -> TC-065 | D71: Admin gán ngoại lệ cho thợ ngoài khu vực/chuyên môn | E71: Đang mở chi tiết Ticket; Admin tắt bộ lọc mặc định để chọn thợ không thỏa điều kiện khu vực/chuyên môn | F71: 1. Admin tắt bộ lọc mặc định 2. Chọn 1 thợ ngoài khu vực/chuyên môn 3. Bấm 'Gán việc' | G71: Thợ không đúng Quận/Huyện hoặc không đúng chuyên môn của Ticket | H71: Hệ thống hiện Pop-up xác nhận override; khi Admin xác nhận, hệ thống gán việc bình thường và lưu lý do override vào log | J71: Block | K71: Cao
A72: =ROW()-6 -> 66 | B72: Tìm kiếm & Điều phối | C72: ="TC-" & TEXT($A72, "000") -> TC-066 | D72: Admin hủy xác nhận Pop-up override khi gán thợ ngoài khu vực/chuyên môn | E72: Pop-up xác nhận override đang hiển thị | F72: 1. Ở Pop-up xác nhận override, bấm 'Hủy' | G72: Thợ không đúng Quận/Huyện hoặc không đúng chuyên môn của Ticket | H72: Thao tác gán việc bị hủy, Ticket vẫn giữ nguyên trạng thái 'unassigned', không có thay đổi nào được lưu | J72: Block | K72: Trung bình
A73: =ROW()-6 -> 67 | B73: Tìm kiếm & Điều phối | C73: ="TC-" & TEXT($A73, "000") -> TC-067 | D73: Kiểm tra Order và Ticket là 2 chuỗi trạng thái độc lập | E73: Ticket đang được xử lý qua nhiều trạng thái (assigned, accepted...) | F73: 1. Theo dõi trạng thái Order trong khi Ticket thay đổi trạng thái nhiều lần (assigned -> unassigned -> assigned...) | H73: Trạng thái Order (VD: confirmed) không bị ảnh hưởng bởi các thay đổi trạng thái của Ticket | J73: Pass | K73: Cao | L73: Bùi Lương Trọng Trí | M73: 46286
A74: =ROW()-6 -> 68 | B74: Tìm kiếm & Điều phối | C74: ="TC-" & TEXT($A74, "000") -> TC-068 | D74: Admin/Điều phối nhận thông báo khi có Ticket mới cần phân bổ | E74: Khách vừa đặt đơn thành công, Ticket vừa được sinh (unassigned) | F74: 1. Khách đặt đơn thành công 2. Kiểm tra Web Notification trên Admin Portal | H74: Admin/Điều phối nhận được thông báo dạng: 'Có 01 đơn hàng mới #[mã đơn] tại [Quận/Huyện] cần phân bổ thợ.' | J74: Block | K74: Cao
A75: =ROW()-6 -> 69 | B75: Tìm kiếm & Điều phối | C75: ="TC-" & TEXT($A75, "000") -> TC-069 | D75: Thợ nhận Push khi Admin gán thợ | E75: Admin vừa gán Ticket cho thợ | F75: 1. Admin bấm 'Gán thợ' 2. Kiểm tra Push App/Sound trên điện thoại thợ | H75: Thợ nhận Push: 'Bạn vừa được điều phối công việc mới tại [Quận/Huyện] vào lúc [Giờ hẹn]. Vui lòng xác nhận.' | J75: Block | K75: Cao
A76: =ROW()-6 -> 70 | B76: Tìm kiếm & Điều phối | C76: ="TC-" & TEXT($A76, "000") -> TC-070 | D76: Khách hàng nhận Push khi thợ bấm Xác nhận nhận việc | E76: Thợ vừa bấm xác nhận Ticket | F76: 1. Thợ bấm 'Xác nhận' 2. Kiểm tra Push trên App khách hàng | H76: Khách hàng nhận Push: 'Kỹ thuật viên [Tên Thợ] đã tiếp nhận đơn hàng của bạn và sẽ có mặt đúng giờ hẹn.' | J76: Block | K76: Cao
A77: =ROW()-6 -> 71 | B77: Tìm kiếm & Điều phối | C77: ="TC-" & TEXT($A77, "000") -> TC-071 | D77: Admin/Điều phối nhận cảnh báo khi thợ Báo bận/Từ chối nhận việc | E77: Thợ vừa bấm Từ chối 1 Ticket | F77: 1. Thợ bấm 'Từ chối' kèm lý do 2. Kiểm tra Web Alert/Sound trên Admin Portal | G77: Lý do: 'Bận việc cá nhân' | H77: Admin nhận cảnh báo: 'Cảnh báo: Thợ [Tên Thợ] vừa từ chối Ticket #[mã] (Lý do: [Lý do]). Vui lòng gán thợ khác.' | J77: Block | K77: Cao
A78: =ROW()-6 -> 72 | B78: Tìm kiếm & Điều phối | C78: ="TC-" & TEXT($A78, "000") -> TC-072 | D78: Thợ (đã được gán) nhận Push khi khách hàng hủy đơn | E78: Ticket đang assigned/accepted cho thợ; khách hàng vừa hủy đơn | F78: 1. Khách hàng bấm 'Hủy đơn' 2. Kiểm tra Push trên App thợ | H78: Thợ nhận Push: 'Đơn hàng tại [Quận/Huyện] vào lúc [Giờ hẹn] đã bị khách hàng hủy.' | J78: Block | K78: Cao
A79: =ROW()-6 -> 73 | B79: Đặt lịch & Đơn hàng | C79: ="TC-" & TEXT($A79, "000") -> TC-073 | D79: Đặt đơn COD với 1 dịch vụ, số lượng mặc định | E79: Khách đã đăng nhập, có địa chỉ đã lưu, dịch vụ đang hoạt động | F79: 1. Mở chi tiết dịch vụ > Chọn Đặt lịch. 2. Chọn địa chỉ, ngày giờ hẹn. 3. Chọn COD > Bấm Xác nhận đặt đơn. | G79: Dịch vụ: Vệ sinh máy lạnh; SL: 1; payment_method: cod | H79: Đơn tạo thành công với orders.status='pending_confirm', payment_status='unpaid'; total_amount = đơn giá × 1. | J79: Pass | K79: Cao | L79: Bùi Lương Trọng Trí | M79: 46287
A80: =ROW()-6 -> 74 | B80: Đặt lịch & Đơn hàng | C80: ="TC-" & TEXT($A80, "000") -> TC-074 | D80: Đặt đơn COD khi tăng số lượng 1 dịch vụ lên nhiều hơn 1 | E80: Khách đã chọn dịch vụ cho phép chọn số lượng | F80: 1. Ở màn đặt lịch, tăng số lượng lên 3. 2. Kiểm tra tổng tiền tạm tính. 3. Chọn COD > Xác nhận đặt đơn. | G80: SL: 3; payment_method: cod | H80: Tổng tiền tạm tính và total_amount của đơn bằng đơn giá × 3; đơn ở trạng thái pending_confirm. | J80: Pass | K80: Cao | L80: Bùi Lương Trọng Trí | M80: 46287
A81: =ROW()-6 -> 75 | B81: Đặt lịch & Đơn hàng | C81: ="TC-" & TEXT($A81, "000") -> TC-075 | D81: Đặt đơn COD với nhiều dịch vụ trong cùng một đơn | E81: Khách đã thêm từ 2 dịch vụ trở lên vào đơn | F81: 1. Chọn dịch vụ A và dịch vụ B. 2. Chọn địa chỉ, ngày giờ hẹn. 3. Chọn COD > Xác nhận đặt đơn. | G81: 2 dịch vụ khác nhau; payment_method: cod | H81: Đơn có đủ 2 dòng dịch vụ, total_amount bằng tổng thành tiền các dòng, orders.status='pending_confirm'. | J81: Pass | K81: Cao | L81: Bùi Lương Trọng Trí | M81: 46287
A82: =ROW()-6 -> 76 | B82: Đặt lịch & Đơn hàng | C82: ="TC-" & TEXT($A82, "000") -> TC-076 | D82: Đặt đơn COD với khung giờ hẹn hợp lệ trong tương lai | E82: Khách đang ở bước chọn ngày giờ hẹn | F82: 1. Chọn ngày mai và một khung giờ còn trống. 2. Chọn COD > Xác nhận đặt đơn. 3. Mở chi tiết đơn vừa tạo. | G82: Ngày hẹn: ngày mai; Giờ hẹn: 09:00 | H82: Đơn lưu đúng ngày giờ hẹn và hiển thị đúng ở chi tiết đơn (App khách và Web Admin). | J82: Pass | K82: Trung bình | L82: Bùi Lương Trọng Trí | M82: 46287
A83: =ROW()-6 -> 77 | B83: Đặt lịch & Đơn hàng | C83: ="TC-" & TEXT($A83, "000") -> TC-077 | D83: Chặn chọn ngày giờ hẹn trong quá khứ | E83: Khách đang ở bước chọn ngày giờ hẹn | F83: 1. Cố chọn ngày đã qua hoặc giờ đã qua trong ngày hôm nay. 2. Bấm Xác nhận đặt đơn. | G83: Ngày hẹn: hôm qua | H83: Không cho chọn mốc thời gian trong quá khứ (ô bị vô hiệu hoặc báo lỗi), không tạo đơn. | J83: Pass | K83: Cao | L83: Bùi Lương Trọng Trí | M83: 46287
A84: =ROW()-6 -> 78 | B84: Đặt lịch & Đơn hàng | C84: ="TC-" & TEXT($A84, "000") -> TC-078 | D84: Chặn đặt đơn COD khi chưa chọn địa chỉ | E84: Khách đã chọn dịch vụ, chưa chọn địa chỉ | F84: 1. Chọn ngày giờ hẹn, chọn COD. 2. Bấm Xác nhận đặt đơn khi chưa có địa chỉ. | G84: Địa chỉ: để trống | H84: Vô hiệu hoá nút "Tiếp theo" để đặt lịch | J84: Pass | K84: Cao | L84: Bùi Lương Trọng Trí | M84: 46287
A85: =ROW()-6 -> 79 | B85: Đặt lịch & Đơn hàng | C85: ="TC-" & TEXT($A85, "000") -> TC-079 | D85: Chặn đặt đơn COD khi chưa chọn ngày giờ hẹn | E85: Khách đã chọn dịch vụ và địa chỉ | F85: 1. Chọn COD. 2. Bấm Xác nhận đặt đơn khi chưa chọn ngày giờ. | G85: Ngày giờ hẹn: để trống | H85: Vô hiệu hoá nút "Tiếp theo" để đặt lịch | J85: Pass | K85: Cao | L85: Bùi Lương Trọng Trí | M85: 46287
A86: =ROW()-6 -> 80 | B86: Đặt lịch & Đơn hàng | C86: ="TC-" & TEXT($A86, "000") -> TC-080 | D86: Đặt đơn COD với địa chỉ đã lưu trong sổ địa chỉ | E86: Khách có ít nhất 2 địa chỉ đã lưu | F86: 1. Ở bước địa chỉ, chọn địa chỉ thứ 2 trong sổ địa chỉ. 2. Chọn giờ hẹn, COD > Xác nhận đặt đơn. | G86: Địa chỉ đã lưu số 2 | H86: Đơn lưu đúng địa chỉ đã chọn, hiển thị khớp ở chi tiết đơn và ticket. | J86: Pass | K86: Trung bình | L86: Bùi Lương Trọng Trí | M86: 46287
A87: =ROW()-6 -> 81 | B87: Đặt lịch & Đơn hàng | C87: ="TC-" & TEXT($A87, "000") -> TC-081 | D87: Thêm địa chỉ mới ngay ở bước đặt đơn rồi đặt COD | E87: Khách đang ở bước chọn địa chỉ | F87: 1. Bấm Thêm địa chỉ mới, nhập đầy đủ thông tin > Lưu. 2. Chọn địa chỉ vừa thêm. 3. Chọn COD > Xác nhận đặt đơn. | G87: Địa chỉ mới hợp lệ | H87: Địa chỉ mới được lưu vào sổ địa chỉ và gắn vào đơn; đơn tạo thành công ở pending_confirm. | J87: Pass | K87: Trung bình | L87: Bùi Lương Trọng Trí | M87: 46287
A88: =ROW()-6 -> 82 | B88: Đặt lịch & Đơn hàng | C88: ="TC-" & TEXT($A88, "000") -> TC-082 | D88: Bấm đúp nút Xác nhận đặt đơn chỉ tạo 1 đơn | E88: Khách đã điền đầy đủ thông tin, chọn COD | F88: 1. Bấm nhanh 2 lần liên tiếp nút Xác nhận đặt đơn. 2. Vào Lịch sử đơn hàng kiểm tra. | G88: payment_method: cod | H88: Chỉ có 1 đơn được tạo, không phát sinh đơn trùng. | J88: Pass | K88: Cao | L88: Bùi Lương Trọng Trí | M88: 46287
A89: =ROW()-6 -> 83 | B89: Đặt lịch & Đơn hàng | C89: ="TC-" & TEXT($A89, "000") -> TC-083 | D89: Mất kết nối mạng khi bấm Xác nhận đặt đơn COD | E89: Khách đã điền đầy đủ thông tin, chọn COD | F89: 1. Tắt mạng trên thiết bị. 2. Bấm Xác nhận đặt đơn. 3. Bật lại mạng, kiểm tra Lịch sử đơn hàng. | G89: Mất mạng | H89: Hiển thị thông báo lỗi "Không thể kết nối với máy chủ. Vui lòng kiểm tra mạng và thử lại", không tạo đơn ngoài ý muốn; khách có thể thử lại sau khi có mạng. | J89: Pass | K89: Trung bình | L89: Bùi Lương Trọng Trí | M89: 46287
A90: =ROW()-6 -> 84 | B90: Đặt lịch & Đơn hàng | C90: ="TC-" & TEXT($A90, "000") -> TC-084 | D90: Chi tiết đơn COD hiển thị đầy đủ thông tin cho khách | E90: Khách có đơn COD vừa tạo | F90: 1. Vào Hoạt động > Chọn đơn COD vừa tạo. | G90: Đơn COD | H90: Chi tiết đơn hiển thị mã đơn, dịch vụ, giá, địa chỉ, ngày giờ hẹn, phương thức COD, trạng thái. | J90: Pass | K90: Trung bình | L90: Bùi Lương Trọng Trí | M90: 46287
... A103: =ROW()-6 -> 97 | B103: Đặt lịch & Đơn hàng | C103: ="TC-" & TEXT($A103, "000") -> TC-097 | D103: Đặt đơn chọn thanh toán COD thành công | E103: Khách hàng đã chọn dịch vụ và địa chỉ | F103: 1. Chọn ngày, giờ hẹn. 2. Chọn phương thức COD. 3. Bấm Xác nhận đặt đơn. | G103: payment_method: cod | H103: Đơn hàng tạo thành công với orders.status='pending_confirm', payment_status='unpaid', không qua pending_payment. | J103: Pass | K103: Cao | L103: Bùi Lương Trọng Trí | M103: 46282
A104: =ROW()-6 -> 98 | B104: Đặt lịch & Đơn hàng | C104: ="TC-" & TEXT($A104, "000") -> TC-098 | D104: Chọn phương thức thanh toán ZaloPay (Online) và tạo đơn | E104: Đang ở bước chọn phương thức thanh toán | F104: 1. Chọn phương thức ZaloPay 2. Bấm tạo đơn 3. Chuyển sang cổng thanh toán | G104: payment_method: zalopay | H104: Đơn hàng được tạo với orders.status='pending_payment', payment_status='unpaid'; chuyển hướng khách sang cổng ZaloPay để thanh toán | J104: Block | K104: Cao
A105: =ROW()-6 -> 99 | B105: Đặt lịch & Đơn hàng | C105: ="TC-" & TEXT($A105, "000") -> TC-099 | D105: Đơn thanh toán online quá 15 phút chưa thanh toán (Payment Timeout) | E105: Đơn tạo chọn ZaloPay đang ở pending_payment | F105: Không hoàn tất thanh toán trên cổng, chờ quá 15 phút. | G105: Thời gian > 15 phút | H105: Hệ thống tự động chuyển orders.status='cancelled' với lý do "Quá thời hạn thanh toán", actor_role='system'. | J105: Block | K105: Cao
A106: =ROW()-6 -> 100 | B106: Đặt lịch & Đơn hàng | C106: ="TC-" & TEXT($A106, "000") -> TC-100 | D106: Admin duyệt đơn hàng Chưa xác nhận | E106: Đơn hàng đang ở pending_confirm | F106: 1. Admin vào Quản lý đơn hàng > Chờ xác nhận. 2. Kiểm tra thông tin đơn. 3. Bấm Xác nhận đơn. | G106: Đơn pending_confirm | H106: orders.status chuyển thành confirmed, tự động sinh 1 bản ghi tickets(status='unassigned'). | J106: Pass | K106: Cao | L106: Bùi Lương Trọng Trí | M106: 46282
A107: =ROW()-6 -> 101 | B107: Đặt lịch & Đơn hàng | C107: ="TC-" & TEXT($A107, "000") -> TC-101 | D107: Admin từ chối/hủy đơn đã thanh toán online ở pending_confirm | E107: Đơn đã trả online (payment_status='paid') | F107: 1. Mở chi tiết đơn pending_confirm. 2. Bấm Hủy đơn. 3. Nhập lý do hủy > Xác nhận. | G107: Lý do: "Khu vực không phục vụ" | H107: orders.status chuyển cancelled, hệ thống tự động kích hoạt lệnh hoàn tiền 100% qua ZaloPay (payment_status='refunded'). | J107: Block | K107: Cao
A108: =ROW()-6 -> 102 | B108: Đặt lịch & Đơn hàng | C108: ="TC-" & TEXT($A108, "000") -> TC-102 | D108: Khách hàng tự hủy đơn khi đang ở pending_confirm | E108: Đơn hàng đang ở trạng thái pending_confirm | F108: 1. Khách vào chi tiết đơn hàng. 2. Bấm Hủy đơn. 3. Chọn lý do và xác nhận hủy. | G108: Lý do hủy hợp lệ | H108: Đơn chuyển orders.status='cancelled', hủy ticket liên quan (nếu có). | J108: Pass | K108: Cao | L108: Bùi Lương Trọng Trí | M108: 46282
A109: =ROW()-6 -> 103 | B109: Đặt lịch & Đơn hàng | C109: ="TC-" & TEXT($A109, "000") -> TC-103 | D109: Nhập ghi chú tùy chọn (customer_note) | E109: Đang ở bước điền thông tin đặt lịch | F109: 1. Nhập nội dung vào ô ghi chú 2. Tiếp tục tạo đơn | G109: Ghi chú: 'Máy lạnh kêu to khi chạy' | H109: Ghi chú được lưu đúng vào đơn hàng (customer_note); trường này không bắt buộc nên để trống vẫn tạo đơn được | J109: Block | K109: thấp
A110: =ROW()-6 -> 104 | B110: Đặt lịch & Đơn hàng | C110: ="TC-" & TEXT($A110, "000") -> TC-104 | D110: Đính kèm ảnh lỗi thiết bị hợp lệ (tối đa 5 ảnh) | E110: Đang ở bước điền thông tin đặt lịch | F110: 1. Đính kèm 5 ảnh mô tả lỗi thiết bị 2. Tiếp tục tạo đơn | G110: 5 ảnh JPG/PNG hợp lệ | H110: Hệ thống chấp nhận, lưu đủ 5 ảnh vào attached_images của đơn hàng | J110: Block | K110: Trung bình
A111: =ROW()-6 -> 105 | B111: Đặt lịch & Đơn hàng | C111: ="TC-" & TEXT($A111, "000") -> TC-105 | D111: Nghiệm thu hoàn tất đơn hàng thanh toán COD | E111: Thợ đã sửa xong, đơn chọn COD | F111: 1. Thợ bấm Yêu cầu nghiệm thu. 2. Thợ tích chọn Đã thu đủ tiền mặt. 3. Admin kiểm tra và bấm Xác nhận hoàn thành. | G111: Thu đủ 100% total_amount | H111: orders.status chuyển completed, payment_status='paid'. Không cho bấm hoàn tất nếu chưa thu đủ tiền. | J111: Pass | K111: Cao | L111: Bùi Lương Trọng Trí | M111: 46282
A112: =ROW()-6 -> 106 | B112: Đặt lịch & Đơn hàng | C112: ="TC-" & TEXT($A112, "000") -> TC-106 | D112: Áp dụng mã Voucher hợp lệ | E112: Tồn tại voucher hợp lệ, còn hiệu lực, đủ điều kiện áp dụng | F112: 1. Ở bước áp Voucher, nhập/chọn mã voucher hợp lệ 2. Xác nhận áp dụng | G112: Voucher: 'Giảm 20%' | H112: Backend lưu voucher_code, tính lại discount_amount và total_amount chính xác theo giá trị voucher | J112: Pass | K112: Cao | L112: Bùi Lương Trọng Trí | M112: 46286
A113: =ROW()-6 -> 107 | B113: Đặt lịch & Đơn hàng | C113: ="TC-" & TEXT($A113, "000") -> TC-107 | D113: Áp dụng mã Voucher không hợp lệ hoặc đã hết hạn | E113: Voucher không tồn tại hoặc đã hết hạn sử dụng | F113: 1. Nhập mã voucher không hợp lệ/hết hạn 2. Xác nhận áp dụng | G113: Voucher: 'HETHAN' | H113: Hệ thống báo không có voucher | J113: Pass | K113: Cao | L113: Bùi Lương Trọng Trí | M113: 46286
A114: =ROW()-6 -> 108 | B114: Đặt lịch & Đơn hàng | C114: ="TC-" & TEXT($A114, "000") -> TC-108 | D114: Admin hủy đơn đã thanh toán online (paid) -> tự động hoàn tiền 100% | E114: Đơn đang pending_confirm với payment_status='paid' (đã thanh toán online) | F114: 1. Admin bấm 'Hủy đơn', nhập lý do 2. Xác nhận | G114: payment_status trước khi hủy: paid | H114: orders.status='cancelled'; hệ thống tự động tạo lệnh hoàn tiền 100% cho khách; payment_status chuyển 'refunded' | J114: Block | K114: Cao
A115: =ROW()-6 -> 109 | B115: Đặt lịch & Đơn hàng | C115: ="TC-" & TEXT($A115, "000") -> TC-109 | D115: Thợ bấm 'Yêu cầu nghiệm thu' sau khi sửa chữa xong | E115: Thợ đang thực hiện Ticket, đã hoàn tất công việc sửa chữa | F115: 1. Thợ bấm 'Yêu cầu nghiệm thu' | H115: Hệ thống ghi nhận yêu cầu nghiệm thu | J115: Block | K115: Cao
A116: =ROW()-6 -> 110 | B116: Đặt lịch & Đơn hàng | C116: ="TC-" & TEXT($A116, "000") -> TC-110 | D116: Kiểm tra công thức tính total_amount | E116: Đơn hàng có subtotal_amount, discount_amount, additional_fee cụ thể | F116: 1. Tạo đơn với subtotal_amount, áp voucher (discount_amount) và additional_fee (nếu có) 2. Kiểm tra total_amount trả về | G116: subtotal: 400.000; discount: 20%; additional_fee: 10% | H116: total_amount = subtotal_amount - discount_amount + additional_fee = 400.000 - (400.000 x 20%) + (400.000 x 10%) = 360.000 | J116: Pass | K116: Cao | L116: Bùi Lương Trọng Trí | M116: 46286
A117: =ROW()-6 -> 111 | B117: Đặt lịch & Đơn hàng | C117: ="TC-" & TEXT($A117, "000") -> TC-111 | D117: Khách hàng nhận Push khi tạo đơn thành công (pending_confirm) | E117: Khách vừa hoàn tất tạo đơn (COD hoặc thanh toán online thành công) | F117: 1. Tạo đơn thành công 2. Kiểm tra Push App trên điện thoại khách | H117: Khách nhận Push: 'Đơn hàng #[Mã_Đơn] đã được gửi thành công và đang chờ ban quản trị xác nhận.' | J117: Block | K117: Cao
A118: =ROW()-6 -> 112 | B118: Đặt lịch & Đơn hàng | C118: ="TC-" & TEXT($A118, "000") -> TC-112 | D118: Admin nhận Web Notification khi có đơn hàng mới cần duyệt | E118: Đơn vừa chuyển sang trạng thái pending_confirm | F118: 1. Đơn hàng mới chuyển pending_confirm 2. Kiểm tra Web Notification trên Admin Portal | H118: Admin nhận thông báo: 'Có 01 đơn hàng mới #[Mã_Đơn] tại [Quận/Huyện] đang chờ xác nhận.' | J118: Block | K118: Cao
...

Sheet Danh sách lỗi 
A1: Danh sách lỗi (Fail)
A3: STT | B3: Module | C3: Test Case ID | D3: Tên Test Case | E3: Điều kiện tiền đề | F3: Bước thực hiện | G3: Dữ liệu test | H3: Kết quả mong đợi | I3: Kết quả thực tế | J3: Trạng thái | K3: Mức độ ưu tiên | L3: Người test | M3: Ngày test
A4: =IFERROR(__xludf.DUMMYFUNCTION("FILTER('Danh sách Test Case'!A7:M1000, 'Danh sách Test Case'!J7:J1000=""Fail"")"),17.0) -> 17 | B4: =IFERROR(__xludf.DUMMYFUNCTION("""COMPUTED_VALUE"""),"Người dùng") -> Người dùng | C4: =IFERROR(__xludf.DUMMYFUNCTION("""COMPUTED_VALUE"""),"TC-017") -> TC-017 | D4: =IFERROR(__xludf.DUMMYFUNCTION("""COMPUTED_VALUE"""),"Thoát App khi đang ở màn hình OTP và quay lại đăng ký cùng SĐT trong vòng 3 phút") -> Thoát App khi đang ở màn hình OTP và quay lại đăng ký cùng SĐT trong vòng 3 phút | E4: =IFERROR(__xludf.DUMMYFUNCTION("""COMPUTED_VALUE"""),"Đã đăng ký với SĐT X (verify='unverified'), OTP cũ còn hạn (< 3 phút)") -> Đã đăng ký với SĐT X (verify='unverified'), OTP cũ còn hạn (< 3 phút) | F4: =IFERROR(__xludf.DUMMYFUNCTION("""COMPUTED_VALUE"""),"1. Thoát App khi đang ở màn hình nhập OTP 2. Mở lại App, nhập lại cùng SĐT X để đăng ký 3. Bấm 'Tiếp tục'") -> 1. Thoát App khi đang ở màn hình nhập OTP 2. Mở lại App, nhập lại cùng SĐT X để đăng ký 3. Bấm 'Tiếp tục' | G4: =IFERROR(__xludf.DUMMYFUNCTION("""COMPUTED_VALUE"""),"SĐT X, OTP cũ còn hạn") -> SĐT X, OTP cũ còn hạn | H4: =IFERROR(__xludf.DUMMYFUNCTION("""COMPUTED_VALUE"""),"Backend nhận diện OTP cũ còn hạn, trả cờ OTP_ALREADY_SENT kèm số giây còn lại; Client vào thẳng màn hình OTP với đếm ngược tiếp tục, không gửi SMS mới") -> Backend nhận diện OTP cũ còn hạn, trả cờ OTP_ALREADY_SENT kèm số giây còn lại; Client vào thẳng màn hình OTP với đếm ngược tiếp tục, không gửi SMS mới | I4: =IFERROR(__xludf.DUMMYFUNCTION("""COMPUTED_VALUE"""),"Hiện thông báo không thể gửi OTP, không quay lại màn hình nhập OTP") -> Hiện thông báo không thể gửi OTP, không quay lại màn hình nhập OTP | J4: =IFERROR(__xludf.DUMMYFUNCTION("""COMPUTED_VALUE"""),"Fail") -> Fail | K4: =IFERROR(__xludf.DUMMYFUNCTION("""COMPUTED_VALUE"""),"Trung bình") -> Trung bình | L4: =IFERROR(__xludf.DUMMYFUNCTION("""COMPUTED_VALUE"""),"Bùi Lương Trọng Trí") -> Bùi Lương Trọng Trí | M4: =IFERROR(__xludf.DUMMYFUNCTION("""COMPUTED_VALUE"""),46283.0) -> 46283

Sheet Tổng hợp 
A1: BÁO CÁO TỔNG HỢP KIỂM THỬ
A3: Dự án / Hệ thống: | B3: FixHub
A4: Phạm vi kiểm thử: | B4: Toàn bộ luồng nghiệp vụ (App Khách hàng, App Thợ, Web Admin)
A5: Thời gian kiểm thử: | B5: 17/09/2026 - 23/09/2026
A6: Người tổng hợp: | B6: Bùi Lương Trọng Trí
A7: Ngày lập báo cáo: | B7: 46289
A9: 1. Thống kê theo trạng thái thực thi
A11: Trạng thái | B11: Số lượng | C11: Tỷ lệ (%)
A12: Pass | B12: =COUNTIF('Danh sách Test Case'!$J:$J, A12) -> 158 | C12: =B12/$B$16 -> 0.50803859
A13: Fail | B13: =COUNTIF('Danh sách Test Case'!$J:$J, A13) -> 1 | C13: =B13/$B$16 -> 0.0032154341
A14: Block | B14: =COUNTIF('Danh sách Test Case'!$J:$J, A14) -> 151 | C14: =B14/$B$16 -> 0.48553055
A15: Chưa test | B15: =COUNTIF('Danh sách Test Case'!$J:$J, A15) -> 1 | C15: =B15/$B$16 -> 0.0032154341
A16: Tổng cộng | B16: =SUM(B12:B15) -> 311 | C16: =SUM(C12:C15) -> 1
A18: Tỷ lệ Pass / số đã thực thi (Pass+Fail): | C18: =B12/(B16 - B15 -B14) -> 0.99371069
A21: 2. Thống kê theo mức độ ưu tiên
A23: Mức độ ưu tiên | B23: Số lượng | C23: Tỷ lệ (%)
A24: Cao | B24: =COUNTIF('Danh sách Test Case'!$K:$K,A24) -> 210 | C24: =B24/$B$16 -> 0.67524116
A25: Trung bình | B25: =COUNTIF('Danh sách Test Case'!$K:$K,A25) -> 89 | C25: =B25/$B$16 -> 0.28617363
A26: thấp | B26: =COUNTIF('Danh sách Test Case'!$K:$K,A26) -> 12 | C26: =B26/$B$16 -> 0.038585209
A29: 3. Thống kê theo Module
A31: Module | B31: Pass | C31: Fail | D31: Block | E31: Chưa test | F31: Tổng
A32: Người dùng | B32: =COUNTIFS('Danh sách Test Case'!$B:$B, $A32, 'Danh sách Test Case'!$J:$J, B$31) -> 22 | C32: =COUNTIFS('Danh sách Test Case'!$B:$B, $A32, 'Danh sách Test Case'!$J:$J, C$31) -> 1 | D32: =COUNTIFS('Danh sách Test Case'!$B:$B, $A32, 'Danh sách Test Case'!$J:$J, D$31) -> 6 | E32: =COUNTIFS('Danh sách Test Case'!$B:$B, $A32, 'Danh sách Test Case'!$J:$J, E$31) -> 0 | F32: =SUM($B32:$E32) -> 29
A33: Thợ & KYC | B33: =COUNTIFS('Danh sách Test Case'!$B:$B, $A33, 'Danh sách Test Case'!$J:$J, B$31) -> 0 | C33: =COUNTIFS('Danh sách Test Case'!$B:$B, $A33, 'Danh sách Test Case'!$J:$J, C$31) -> 0 | D33: =COUNTIFS('Danh sách Test Case'!$B:$B, $A33, 'Danh sách Test Case'!$J:$J, D$31) -> 6 | E33: =COUNTIFS('Danh sách Test Case'!$B:$B, $A33, 'Danh sách Test Case'!$J:$J, E$31) -> 0 | F33: =SUM($B33:$E33) -> 6
A34: Tìm kiếm & Điều phối | B34: =COUNTIFS('Danh sách Test Case'!$B:$B, $A34, 'Danh sách Test Case'!$J:$J, B$31) -> 22 | C34: =COUNTIFS('Danh sách Test Case'!$B:$B, $A34, 'Danh sách Test Case'!$J:$J, C$31) -> 0 | D34: =COUNTIFS('Danh sách Test Case'!$B:$B, $A34, 'Danh sách Test Case'!$J:$J, D$31) -> 15 | E34: =COUNTIFS('Danh sách Test Case'!$B:$B, $A34, 'Danh sách Test Case'!$J:$J, E$31) -> 0 | F34: =SUM($B34:$E34) -> 37
A35: Đặt lịch & Đơn hàng | B35: =COUNTIFS('Danh sách Test Case'!$B:$B, $A35, 'Danh sách Test Case'!$J:$J, B$31) -> 31 | C35: =COUNTIFS('Danh sách Test Case'!$B:$B, $A35, 'Danh sách Test Case'!$J:$J, C$31) -> 0 | D35: =COUNTIFS('Danh sách Test Case'!$B:$B, $A35, 'Danh sách Test Case'!$J:$J, D$31) -> 11 | E35: =COUNTIFS('Danh sách Test Case'!$B:$B, $A35, 'Danh sách Test Case'!$J:$J, E$31) -> 0 | F35: =SUM($B35:$E35) -> 42
A36: Phát sinh dịch vụ (OCR) | B36: =COUNTIFS('Danh sách Test Case'!$B:$B, $A36, 'Danh sách Test Case'!$J:$J, B$31) -> 0 | C36: =COUNTIFS('Danh sách Test Case'!$B:$B, $A36, 'Danh sách Test Case'!$J:$J, C$31) -> 0 | D36: =COUNTIFS('Danh sách Test Case'!$B:$B, $A36, 'Danh sách Test Case'!$J:$J, D$31) -> 23 | E36: =COUNTIFS('Danh sách Test Case'!$B:$B, $A36, 'Danh sách Test Case'!$J:$J, E$31) -> 0 | F36: =SUM($B36:$E36) -> 23
A37: Thanh toán & Ví | B37: =COUNTIFS('Danh sách Test Case'!$B:$B, $A37, 'Danh sách Test Case'!$J:$J, B$31) -> 20 | C37: =COUNTIFS('Danh sách Test Case'!$B:$B, $A37, 'Danh sách Test Case'!$J:$J, C$31) -> 0 | D37: =COUNTIFS('Danh sách Test Case'!$B:$B, $A37, 'Danh sách Test Case'!$J:$J, D$31) -> 16 | E37: =COUNTIFS('Danh sách Test Case'!$B:$B, $A37, 'Danh sách Test Case'!$J:$J, E$31) -> 1 | F37: =SUM($B37:$E37) -> 37
A38: Đánh giá & Phản hồi | B38: =COUNTIFS('Danh sách Test Case'!$B:$B, $A38, 'Danh sách Test Case'!$J:$J, B$31) -> 0 | C38: =COUNTIFS('Danh sách Test Case'!$B:$B, $A38, 'Danh sách Test Case'!$J:$J, C$31) -> 0 | D38: =COUNTIFS('Danh sách Test Case'!$B:$B, $A38, 'Danh sách Test Case'!$J:$J, D$31) -> 17 | E38: =COUNTIFS('Danh sách Test Case'!$B:$B, $A38, 'Danh sách Test Case'!$J:$J, E$31) -> 0 | F38: =SUM($B38:$E38) -> 17
A39: Khiếu nại & Bảo hành | B39: =COUNTIFS('Danh sách Test Case'!$B:$B, $A39, 'Danh sách Test Case'!$J:$J, B$31) -> 0 | C39: =COUNTIFS('Danh sách Test Case'!$B:$B, $A39, 'Danh sách Test Case'!$J:$J, C$31) -> 0 | D39: =COUNTIFS('Danh sách Test Case'!$B:$B, $A39, 'Danh sách Test Case'!$J:$J, D$31) -> 16 | E39: =COUNTIFS('Danh sách Test Case'!$B:$B, $A39, 'Danh sách Test Case'!$J:$J, E$31) -> 0 | F39: =SUM($B39:$E39) -> 16
A40: Chat Khách - Thợ | B40: =COUNTIFS('Danh sách Test Case'!$B:$B, $A40, 'Danh sách Test Case'!$J:$J, B$31) -> 0 | C40: =COUNTIFS('Danh sách Test Case'!$B:$B, $A40, 'Danh sách Test Case'!$J:$J, C$31) -> 0 | D40: =COUNTIFS('Danh sách Test Case'!$B:$B, $A40, 'Danh sách Test Case'!$J:$J, D$31) -> 22 | E40: =COUNTIFS('Danh sách Test Case'!$B:$B, $A40, 'Danh sách Test Case'!$J:$J, E$31) -> 0 | F40: =SUM($B40:$E40) -> 22
A41: Quản trị hệ thống | B41: =COUNTIFS('Danh sách Test Case'!$B:$B, $A41, 'Danh sách Test Case'!$J:$J, B$31) -> 63 | C41: =COUNTIFS('Danh sách Test Case'!$B:$B, $A41, 'Danh sách Test Case'!$J:$J, C$31) -> 0 | D41: =COUNTIFS('Danh sách Test Case'!$B:$B, $A41, 'Danh sách Test Case'!$J:$J, D$31) -> 19 | E41: =COUNTIFS('Danh sách Test Case'!$B:$B, $A41, 'Danh sách Test Case'!$J:$J, E$31) -> 0 | F41: =SUM($B41:$E41) -> 82
A42: Tổng cộng | B42: =SUM(Bảng_Thống_kê_theo_Module[Pass]) -> 158 | C42: =SUM(Bảng_Thống_kê_theo_Module[Fail]) -> 1 | D42: =SUM(Bảng_Thống_kê_theo_Module[Block]) -> 151 | E42: =SUM(Bảng_Thống_kê_theo_Module[Chưa test]) -> 1 | F42: =SUM(Bảng_Thống_kê_theo_Module[[#TOTALS],[Pass]:[Chưa test]]) -> 311
